LICENSE.rst
MANIFEST.in
Makefile
NEWS.rst
README.rst
TODO.rst
requirements-dev.txt
requirements-test.txt
setup.cfg
setup.py
doc/api.rst
doc/conf.py
doc/developer.rst
doc/index.rst
doc/installation.rst
doc/license.rst
doc/news.rst
doc/user.rst
plyvel/__init__.py
plyvel/_plyvel.cpp
plyvel/_plyvel.pyx
plyvel/_version.py
plyvel/comparator.cpp
plyvel/comparator.h
plyvel/comparator.pxd
plyvel/leveldb.pxd
plyvel_wx.egg-info/PKG-INFO
plyvel_wx.egg-info/SOURCES.txt
plyvel_wx.egg-info/dependency_links.txt
plyvel_wx.egg-info/top_level.txt
test/__init__.py
test/test_plyvel.py